pytracepath.py
pytracepath_keiichishima-0.1.1.data/scripts/pytracepath
pytracepath_keiichishima-0.1.1.dist-info/LICENSE
pytracepath_keiichishima-0.1.1.dist-info/METADATA
pytracepath_keiichishima-0.1.1.dist-info/WHEEL
pytracepath_keiichishima-0.1.1.dist-info/top_level.txt
pytracepath_keiichishima-0.1.1.dist-info/RECORD
