Metadata-Version: 2.1
Name: pytracepath-keiichishima
Version: 0.1.1
Summary: Tracepath implemented in Python3
Home-page: https://github.com/keiichishima/pytracepath
Author: Keiichi SHIMA
Author-email: keiichi@iijlab.net
License: UNKNOWN
Platform: UNKNOWN
Classifier: Intended Audience :: Developers
Classifier: Intended Audience :: System Administrators
Classifier: License :: OSI Approved :: MIT License
Classifier: Operating System :: POSIX :: Linux
Classifier: Programming Language :: Python :: 3
Classifier: Topic :: Internet
Classifier: Topic :: Software Development :: Libraries :: Python Modules
Classifier: Topic :: System :: Networking
Classifier: Topic :: System :: Systems Administration
Requires-Python: >=3.7
